school_mos/Types.py
school_mos/__init__.py
school_mos/errors.py
school_mos/main.py
school_mos/user_auth.py
school_mos-1.0.dist-info/LICENSE
school_mos-1.0.dist-info/METADATA
school_mos-1.0.dist-info/WHEEL
school_mos-1.0.dist-info/top_level.txt
school_mos-1.0.dist-info/RECORD
