Metadata-Version: 2.1
Name: school-mos
Version: 1.0
Summary: Эта библиотека позволяет получить легкий доступ к ресурсам Московской Электронной Школы, в обход учебного портала.
Author-email: kester4 <forblitzilya@gmail.com>
Project-URL: Homepage, https://github.com/kester4/school_mos
Project-URL: Bug Tracker, https://github.com/kester4/school_mos/issues
Classifier: Programming Language :: Python :: 3
Classifier: License :: OSI Approved :: MIT License
Classifier: Operating System :: OS Independent
Requires-Python: >=3.10
License-File: LICENSE
Requires-Dist: requests
Requires-Dist: selenium
Requires-Dist: pydantic
